ConvexTrader/Portfolio.py
ConvexTrader/Trade.py
ConvexTrader/__init__.py
ConvexTrader/multi_period_optimization.py
ConvexTrader/portfolio_exceptions.py
ConvexTrader/single_period_optimization.py
tests/__init__.py
tests/conftest.py
tests/test_class_initialization.py
tests/test_multi_period_optimization.py
tests/test_single_period_optimization.py
ConvexTrader-0.0.3.dist-info/LICENSE
ConvexTrader-0.0.3.dist-info/METADATA
ConvexTrader-0.0.3.dist-info/WHEEL
ConvexTrader-0.0.3.dist-info/top_level.txt
ConvexTrader-0.0.3.dist-info/RECORD
