Metadata-Version: 2.2
Name: ConvexTrader
Version: 0.0.3
Summary: A collection of SAT and SMT solvers for solving Sudoku puzzles
Home-page: https://acquantclub.com/ConvexTrader
Author: Liam Davis, Tairan 'Ryan' Ji, Allison Klinger, Surya Rao
Author-email: ljdavis27@amherst.edu, tji26@amherst.edu, aklinger27@amherst.edu, srao28@amherst.edu
License: MIT
Classifier: Programming Language :: Python :: 3
Classifier: License :: OSI Approved :: MIT License
Classifier: Operating System :: OS Independent
Requires-Python: >=3.9
License-File: LICENSE
Requires-Dist: cvxpy
Requires-Dist: numpy
Dynamic: author
Dynamic: author-email
Dynamic: classifier
Dynamic: description
Dynamic: description-content-type
Dynamic: home-page
Dynamic: license
Dynamic: requires-dist
Dynamic: requires-python
Dynamic: summary
